pythaispell/__init__.py
pythaispell/sp.model
pythaispell-0.1.dist-info/LICENSE
pythaispell-0.1.dist-info/METADATA
pythaispell-0.1.dist-info/WHEEL
pythaispell-0.1.dist-info/top_level.txt
pythaispell-0.1.dist-info/RECORD
