Metadata-Version: 2.1
Name: pythaispell
Version: 0.1
Summary: Thai Spell Check
Home-page: https://github.com/wannaphongcom/Thai_Spell_Check
Author: Wannaphong Phatthiyaphaibun
Author-email: wannaphong@kkumail.com
License: Apache Software License 2.0
Keywords: promptpay
Platform: UNKNOWN
Classifier: Development Status :: 3 - Alpha
Classifier: Intended Audience :: Developers
Classifier: License :: OSI Approved :: Apache Software License
Classifier: Programming Language :: Python :: Implementation
Requires-Dist: pythainlp
Requires-Dist: sklearn-crfsuite
